{"v":5,"entries":{"question-attachment--playground":{"type":"story","subtype":"story","id":"question-attachment--playground","name":"Playground","title":"Question/Attachment","importPath":"./stories/question/attachment.playground.stories.tsx","tags":["dev","test"],"exportName":"Playground"},"question-boolean--playground":{"type":"story","subtype":"story","id":"question-boolean--playground","name":"Playground","title":"Question/Boolean","importPath":"./stories/question/boolean.playground.stories.tsx","tags":["dev","test"],"exportName":"Playground"},"question-coding--playground":{"type":"story","subtype":"story","id":"question-coding--playground","name":"Playground","title":"Question/Coding","importPath":"./stories/question/coding.playground.stories.tsx","tags":["dev","test"],"exportName":"Playground"},"question-date--playground":{"type":"story","subtype":"story","id":"question-date--playground","name":"Playground","title":"Question/Date","importPath":"./stories/question/date.playground.stories.tsx","tags":["dev","test"],"exportName":"Playground"},"question-datetime--playground":{"type":"story","subtype":"story","id":"question-datetime--playground","name":"Playground","title":"Question/DateTime","importPath":"./stories/question/dateTime.playground.stories.tsx","tags":["dev","test"],"exportName":"Playground"},"question-decimal--playground":{"type":"story","subtype":"story","id":"question-decimal--playground","name":"Playground","title":"Question/Decimal","importPath":"./stories/question/decimal.playground.stories.tsx","tags":["dev","test"],"exportName":"Playground"},"question-integer--playground":{"type":"story","subtype":"story","id":"question-integer--playground","name":"Playground","title":"Question/Integer","importPath":"./stories/question/integer.playground.stories.tsx","tags":["dev","test"],"exportName":"Playground"},"question-quantity--playground":{"type":"story","subtype":"story","id":"question-quantity--playground","name":"Playground","title":"Question/Quantity","importPath":"./stories/question/quantity.playground.stories.tsx","tags":["dev","test"],"exportName":"Playground"},"question-reference--playground":{"type":"story","subtype":"story","id":"question-reference--playground","name":"Playground","title":"Question/Reference","importPath":"./stories/question/reference.playground.stories.tsx","tags":["dev","test"],"exportName":"Playground"},"question-string--playground":{"type":"story","subtype":"story","id":"question-string--playground","name":"Playground","title":"Question/String","importPath":"./stories/question/string.playground.stories.tsx","tags":["dev","test"],"exportName":"Playground"},"question-text--playground":{"type":"story","subtype":"story","id":"question-text--playground","name":"Playground","title":"Question/Text","importPath":"./stories/question/text.playground.stories.tsx","tags":["dev","test"],"exportName":"Playground"},"question-time--playground":{"type":"story","subtype":"story","id":"question-time--playground","name":"Playground","title":"Question/Time","importPath":"./stories/question/time.playground.stories.tsx","tags":["dev","test"],"exportName":"Playground"},"question-url--playground":{"type":"story","subtype":"story","id":"question-url--playground","name":"Playground","title":"Question/URL","importPath":"./stories/question/url.playground.stories.tsx","tags":["dev","test"],"exportName":"Playground"},"samples--basic-text-inputs":{"type":"story","subtype":"story","id":"samples--basic-text-inputs","name":"Basic Text Inputs","title":"Samples","importPath":"./stories/samples/samples.stories.tsx","tags":["dev","test"],"exportName":"BasicTextInputs"},"samples--boolean-enable-when":{"type":"story","subtype":"story","id":"samples--boolean-enable-when","name":"Boolean Enable When","title":"Samples","importPath":"./stories/samples/samples.stories.tsx","tags":["dev","test"],"exportName":"BooleanEnableWhen"},"samples--numeric-thresholds":{"type":"story","subtype":"story","id":"samples--numeric-thresholds","name":"Numeric Thresholds","title":"Samples","importPath":"./stories/samples/samples.stories.tsx","tags":["dev","test"],"exportName":"NumericThresholds"},"samples--numeric-units":{"type":"story","subtype":"story","id":"samples--numeric-units","name":"Numeric Units","title":"Samples","importPath":"./stories/samples/samples.stories.tsx","tags":["dev","test"],"exportName":"NumericUnits"},"samples--quantity-unit-options":{"type":"story","subtype":"story","id":"samples--quantity-unit-options","name":"Quantity Unit Options","title":"Samples","importPath":"./stories/samples/samples.stories.tsx","tags":["dev","test"],"exportName":"QuantityUnitOptions"},"samples--help-controls":{"type":"story","subtype":"story","id":"samples--help-controls","name":"Help Controls","title":"Samples","importPath":"./stories/samples/samples.stories.tsx","tags":["dev","test"],"exportName":"HelpControls"},"samples--repeating-question-answers":{"type":"story","subtype":"story","id":"samples--repeating-question-answers","name":"Repeating Question Answers","title":"Samples","importPath":"./stories/samples/samples.stories.tsx","tags":["dev","test"],"exportName":"RepeatingQuestionAnswers"},"samples--repeating-group-instances":{"type":"story","subtype":"story","id":"samples--repeating-group-instances","name":"Repeating Group Instances","title":"Samples","importPath":"./stories/samples/samples.stories.tsx","tags":["dev","test"],"exportName":"RepeatingGroupInstances"},"samples--nested-follow-ups":{"type":"story","subtype":"story","id":"samples--nested-follow-ups","name":"Nested Follow Ups","title":"Samples","importPath":"./stories/samples/samples.stories.tsx","tags":["dev","test"],"exportName":"NestedFollowUps"},"samples--static-initials":{"type":"story","subtype":"story","id":"samples--static-initials","name":"Static Initials","title":"Samples","importPath":"./stories/samples/samples.stories.tsx","tags":["dev","test"],"exportName":"StaticInitials"},"samples--expression-initial-defaults":{"type":"story","subtype":"story","id":"samples--expression-initial-defaults","name":"Expression Initial Defaults","title":"Samples","importPath":"./stories/samples/samples.stories.tsx","tags":["dev","test"],"exportName":"ExpressionInitialDefaults"},"samples--expression-calculated":{"type":"story","subtype":"story","id":"samples--expression-calculated","name":"Expression Calculated","title":"Samples","importPath":"./stories/samples/samples.stories.tsx","tags":["dev","test"],"exportName":"ExpressionCalculated"},"samples--expression-enable-when":{"type":"story","subtype":"story","id":"samples--expression-enable-when","name":"Expression Enable When","title":"Samples","importPath":"./stories/samples/samples.stories.tsx","tags":["dev","test"],"exportName":"ExpressionEnableWhen"},"samples--expression-dynamic-bounds":{"type":"story","subtype":"story","id":"samples--expression-dynamic-bounds","name":"Expression Dynamic Bounds","title":"Samples","importPath":"./stories/samples/samples.stories.tsx","tags":["dev","test"],"exportName":"ExpressionDynamicBounds"},"samples--expression-dynamic-behavior":{"type":"story","subtype":"story","id":"samples--expression-dynamic-behavior","name":"Expression Dynamic Behavior","title":"Samples","importPath":"./stories/samples/samples.stories.tsx","tags":["dev","test"],"exportName":"ExpressionDynamicBehavior"},"samples--expression-dynamic-quantity":{"type":"story","subtype":"story","id":"samples--expression-dynamic-quantity","name":"Expression Dynamic Quantity","title":"Samples","importPath":"./stories/samples/samples.stories.tsx","tags":["dev","test"],"exportName":"ExpressionDynamicQuantity"},"samples--answer-options":{"type":"story","subtype":"story","id":"samples--answer-options","name":"Answer Options","title":"Samples","importPath":"./stories/samples/samples.stories.tsx","tags":["dev","test"],"exportName":"AnswerOptions"},"samples--answer-expressions":{"type":"story","subtype":"story","id":"samples--answer-expressions","name":"Answer Expressions","title":"Samples","importPath":"./stories/samples/samples.stories.tsx","tags":["dev","test"],"exportName":"AnswerExpressions"},"samples--validation":{"type":"story","subtype":"story","id":"samples--validation","name":"Validation","title":"Samples","importPath":"./stories/samples/samples.stories.tsx","tags":["dev","test"],"exportName":"Validation"},"samples--target-constraints":{"type":"story","subtype":"story","id":"samples--target-constraints","name":"Target Constraints","title":"Samples","importPath":"./stories/samples/samples.stories.tsx","tags":["dev","test"],"exportName":"TargetConstraints"},"samples--answer-constraints":{"type":"story","subtype":"story","id":"samples--answer-constraints","name":"Answer Constraints","title":"Samples","importPath":"./stories/samples/samples.stories.tsx","tags":["dev","test"],"exportName":"AnswerConstraints"},"samples--answer-value-set":{"type":"story","subtype":"story","id":"samples--answer-value-set","name":"Answer Value Set","title":"Samples","importPath":"./stories/samples/samples.stories.tsx","tags":["dev","test"],"exportName":"AnswerValueSet"},"samples--item-control-matrix":{"type":"story","subtype":"story","id":"samples--item-control-matrix","name":"Item Control Matrix","title":"Samples","importPath":"./stories/samples/samples.stories.tsx","tags":["dev","test"],"exportName":"ItemControlMatrix"}}}